replace_value_txt/__init__.py
replace_value_txt/replace_value_txt.py
replace_value_txt-1.0.0.dist-info/LICENSE
replace_value_txt-1.0.0.dist-info/METADATA
replace_value_txt-1.0.0.dist-info/WHEEL
replace_value_txt-1.0.0.dist-info/top_level.txt
replace_value_txt-1.0.0.dist-info/RECORD
