Metadata-Version: 2.1
Name: replace-value-txt
Version: 1.0.0
Summary: UNKNOWN
Home-page: https://github.com/BrunoASN/beaufort-scale
Author: Bruno Nascimento
Author-email: bruno_freddy@hotmail.com
License: MIT
Project-URL: Código fonte, https://github.com/BrunoASNascimento/replace_value_txt
Project-URL: Download, https://github.com/BrunoASNascimento/replace_value_txt/archive/main.zip
Keywords: replace
Platform: UNKNOWN
Classifier: Development Status :: 5 - Production/Stable
Classifier: Intended Audience :: Developers
Classifier: License :: OSI Approved :: MIT License
Classifier: Natural Language :: Portuguese (Brazilian)
Classifier: Operating System :: OS Independent
Classifier: Topic :: Software Development :: Internationalization
Requires-Python: >=3.6
